pyjson/__init__.py
pyjson/pyjson.py
pyjson-1.4.0.dist-info/LICENSE
pyjson-1.4.0.dist-info/METADATA
pyjson-1.4.0.dist-info/WHEEL
pyjson-1.4.0.dist-info/top_level.txt
pyjson-1.4.0.dist-info/RECORD
