Metadata-Version: 2.1
Name: pyjson
Version: 1.4.0
Summary: Compare the similarities between two JSONs.
Home-page: https://github.com/leeyoshinari/Small_Tool/tree/master/pyjson
Author: leeyoshinari
Author-email: leeyoshinari@outlook.com
License: UNKNOWN
Keywords: pip,pyjson,logging
Platform: UNKNOWN
Classifier: License :: OSI Approved :: MIT License
Classifier: Intended Audience :: Developers
Classifier: Operating System :: OS Independent
Classifier: Programming Language :: Python
Classifier: Programming Language :: Python :: 3
Classifier: Programming Language :: Python :: 3.8
Classifier: Programming Language :: Python :: 3.9
Classifier: Programming Language :: Python :: 3.10
License-File: LICENSE
